markdown2feishu/__init__.py
markdown2feishu/blocks.py
markdown2feishu/cli.py
markdown2feishu/client.py
markdown2feishu/config.py
markdown2feishu/converter.py
markdown2feishu-0.1.1.dist-info/METADATA
markdown2feishu-0.1.1.dist-info/WHEEL
markdown2feishu-0.1.1.dist-info/entry_points.txt
markdown2feishu-0.1.1.dist-info/licenses/LICENSE
markdown2feishu-0.1.1.dist-info/RECORD
