Metadata-Version: 2.4
Name: markdown2feishu
Version: 0.1.1
Summary: Convert Markdown to Feishu/Lark documents
Project-URL: Homepage, https://github.com/baoyudu/markdown2feishu
Project-URL: Documentation, https://github.com/baoyudu/markdown2feishu#readme
Project-URL: Repository, https://github.com/baoyudu/markdown2feishu
Author-email: Bao Yu <baoyudu@outlook.com>
License-Expression: MIT
License-File: LICENSE
Keywords: converter,document,feishu,lark,markdown
Classifier: Development Status :: 3 - Alpha
Classifier: Intended Audience :: Developers
Classifier: License :: OSI Approved :: MIT License
Classifier: Programming Language :: Python :: 3
Classifier: Programming Language :: Python :: 3.10
Classifier: Programming Language :: Python :: 3.11
Classifier: Programming Language :: Python :: 3.12
Requires-Python: >=3.10
Requires-Dist: httpx>=0.24.0
Requires-Dist: mistune>=3.0.0
Requires-Dist: tomli>=2.0.0; python_version < '3.11'
Provides-Extra: cli
Requires-Dist: click>=8.0.0; extra == 'cli'
Provides-Extra: dev
Requires-Dist: pytest-asyncio>=0.21.0; extra == 'dev'
Requires-Dist: pytest>=7.0.0; extra == 'dev'
Requires-Dist: ruff>=0.1.0; extra == 'dev'
